{
  "cursorId": 0,
  "totalCount": 3,
  "cards": [
    {
      "id": 0,
      "title": "테스트 카드",
      "description": "테스트 카드 1",
      "tags": ["백엔드", "프론트엔드"],
      "dueDate": "2024.03.01",
      "assignee": {
        "profileImageUrl": "/temp/tempCardProfile.svg",
        "nickname": "테스터",
        "id": 0
      },
      "imageUrl": "/temp/tempCardImage.png",
      "teamId": "3-3",
      "columnId": 0,
      "createdAt": "2024-02-02T11:30:47.530Z",
      "updatedAt": "2024-02-02T11:30:47.530Z"
    },
    {
      "id": 1,
      "title": "테스트 카드2",
      "description": "테스트 카드 2",
      "tags": ["프론트"],
      "dueDate": "2024.03.01",
      "assignee": {
        "profileImageUrl": "/temp/tempCardProfile.svg",
        "nickname": "테스터2",
        "id": 1
      },
      "imageUrl": "",
      "teamId": "3-3",
      "columnId": 0,
      "createdAt": "2024-02-02T12:30:47.530Z",
      "updatedAt": "2024-02-02T12:30:47.530Z"
    }
  ]
}
